{
  "data": {
    "attachments": {},
    "author_id": "1191237542797959168",
    "conversation_id": "1800349361043386580",
    "created_at": "2024-06-11T15:02:45.000Z",
    "edit_controls": {
      "editable_until": "2024-06-11T16:02:45.000Z",
      "edits_remaining": 5,
      "is_edit_eligible": false
    },
    "edit_history_tweet_ids": [
      "1800544203090583614"
    ],
    "entities": {
      "mentions": [
        {
          "end": 7,
          "id": "1739391734491086848",
          "start": 0,
          "username": "IZLA00"
        }
      ]
    },
    "geo": {},
    "id": "1800544203090583614",
    "in_reply_to_user_id": "1739391734491086848",
    "lang": "zh",
    "possibly_sensitive": false,
    "public_metrics": {
      "bookmark_count": 0,
      "impression_count": 0,
      "like_count": 0,
      "quote_count": 0,
      "reply_count": 0,
      "retweet_count": 0
    },
    "referenced_tweets": [
      {
        "id": "1800349361043386580",
        "type": "replied_to"
      }
    ],
    "reply_settings": "everyone",
    "text": "@IZLA00 每周五天早八人在此😇"
  },
  "includes": {
    "tweets": [
      {
        "attachments": {},
        "author_id": "1191237542797959168",
        "conversation_id": "1800349361043386580",
        "created_at": "2024-06-11T15:02:45.000Z",
        "edit_controls": {
          "editable_until": "2024-06-11T16:02:45.000Z",
          "edits_remaining": 5,
          "is_edit_eligible": false
        },
        "edit_history_tweet_ids": [
          "1800544203090583614"
        ],
        "entities": {
          "mentions": [
            {
              "end": 7,
              "id": "1739391734491086848",
              "start": 0,
              "username": "IZLA00"
            }
          ]
        },
        "geo": {},
        "id": "1800544203090583614",
        "in_reply_to_user_id": "1739391734491086848",
        "lang": "zh",
        "possibly_sensitive": false,
        "public_metrics": {
          "bookmark_count": 0,
          "impression_count": 0,
          "like_count": 0,
          "quote_count": 0,
          "reply_count": 0,
          "retweet_count": 0
        },
        "referenced_tweets": [
          {
            "id": "1800349361043386580",
            "type": "replied_to"
          }
        ],
        "reply_settings": "everyone",
        "text": "@IZLA00 每周五天早八人在此😇"
      },
      {
        "attachments": {
          "media_keys": [
            "3_1800349350138085376"
          ]
        },
        "author_id": "1739391734491086848",
        "conversation_id": "1800349361043386580",
        "created_at": "2024-06-11T02:08:31.000Z",
        "edit_controls": {
          "editable_until": "2024-06-11T03:08:31.000Z",
          "edits_remaining": 5,
          "is_edit_eligible": true
        },
        "edit_history_tweet_ids": [
          "1800349361043386580"
        ],
        "entities": {
          "urls": [
            {
              "display_url": "pic.twitter.com/RxJDGHSDWp",
              "end": 23,
              "expanded_url": "https://twitter.com/IZLA00/status/1800349361043386580/photo/1",
              "media_key": "3_1800349350138085376",
              "start": 0,
              "url": "https://t.co/RxJDGHSDWp"
            }
          ]
        },
        "geo": {},
        "id": "1800349361043386580",
        "lang": "zxx",
        "possibly_sensitive": false,
        "public_metrics": {
          "bookmark_count": 0,
          "impression_count": 601,
          "like_count": 26,
          "quote_count": 0,
          "reply_count": 3,
          "retweet_count": 0
        },
        "reply_settings": "everyone",
        "text": "https://t.co/RxJDGHSDWp"
      }
    ],
    "users": [
      {
        "created_at": "2019-11-04T06:15:50.000Z",
        "description": "好想养只猫猫啊，没有猫猫的失败人",
        "entities": {
          "url": {
            "urls": [
              {
                "display_url": "google.com",
                "end": 23,
                "expanded_url": "http://www.google.com",
                "start": 0,
                "url": "https://t.co/wHF6m2Z9XX"
              }
            ]
          }
        },
        "id": "1191237542797959168",
        "location": "星河",
        "name": "Siper",
        "pinned_tweet_id": "1799983099612365010",
        "profile_image_url": "https://pbs.twimg.com/profile_images/1738764930801979392/RslNhxWV_normal.jpg",
        "protected": false,
        "public_metrics": {
          "followers_count": 108,
          "following_count": 337,
          "like_count": 638,
          "listed_count": 1,
          "tweet_count": 1685
        },
        "url": "https://t.co/wHF6m2Z9XX",
        "username": "Siperistic",
        "verified": false
      },
      {
        "created_at": "2023-12-25T21:04:51.000Z",
        "description": "不涉三聊天机器人isla/🚪120+（私信赞赏码）/没有💰私信也一样的。/爱你们！🥺",
        "id": "1739391734491086848",
        "location": "32g的硬盘里",
        "name": "isla.exe",
        "pinned_tweet_id": "1800009985633710574",
        "profile_image_url": "https://pbs.twimg.com/profile_images/1799814081932607488/ASe5NH8p_normal.jpg",
        "protected": false,
        "public_metrics": {
          "followers_count": 1276,
          "following_count": 1270,
          "like_count": 8241,
          "listed_count": 4,
          "tweet_count": 8043
        },
        "username": "IZLA00",
        "verified": false
      }
    ]
  }
}