{
  "data": {
    "attachments": {},
    "author_id": "1191237542797959168",
    "conversation_id": "1798652737896509551",
    "created_at": "2024-06-08T11:45:07.000Z",
    "edit_controls": {
      "editable_until": "2024-06-08T12:45:07.000Z",
      "edits_remaining": 5,
      "is_edit_eligible": false
    },
    "edit_history_tweet_ids": [
      "1799407305089523963"
    ],
    "entities": {
      "mentions": [
        {
          "end": 12,
          "id": "1675904773646848000",
          "start": 0,
          "username": "Romi_nyaO_o"
        }
      ]
    },
    "geo": {},
    "id": "1799407305089523963",
    "in_reply_to_user_id": "1675904773646848000",
    "lang": "zh",
    "possibly_sensitive": false,
    "public_metrics": {
      "bookmark_count": 0,
      "impression_count": 0,
      "like_count": 0,
      "quote_count": 0,
      "reply_count": 0,
      "retweet_count": 0
    },
    "referenced_tweets": [
      {
        "id": "1798652737896509551",
        "type": "replied_to"
      }
    ],
    "reply_settings": "everyone",
    "text": "@Romi_nyaO_o 原来我的对手都这么强😇"
  },
  "includes": {
    "tweets": [
      {
        "attachments": {},
        "author_id": "1191237542797959168",
        "conversation_id": "1798652737896509551",
        "created_at": "2024-06-08T11:45:07.000Z",
        "edit_controls": {
          "editable_until": "2024-06-08T12:45:07.000Z",
          "edits_remaining": 5,
          "is_edit_eligible": false
        },
        "edit_history_tweet_ids": [
          "1799407305089523963"
        ],
        "entities": {
          "mentions": [
            {
              "end": 12,
              "id": "1675904773646848000",
              "start": 0,
              "username": "Romi_nyaO_o"
            }
          ]
        },
        "geo": {},
        "id": "1799407305089523963",
        "in_reply_to_user_id": "1675904773646848000",
        "lang": "zh",
        "possibly_sensitive": false,
        "public_metrics": {
          "bookmark_count": 0,
          "impression_count": 0,
          "like_count": 0,
          "quote_count": 0,
          "reply_count": 0,
          "retweet_count": 0
        },
        "referenced_tweets": [
          {
            "id": "1798652737896509551",
            "type": "replied_to"
          }
        ],
        "reply_settings": "everyone",
        "text": "@Romi_nyaO_o 原来我的对手都这么强😇"
      },
      {
        "attachments": {
          "media_keys": [
            "3_1798652730241892353",
            "3_1798652730233540608"
          ]
        },
        "author_id": "1675904773646848000",
        "context_annotations": [
          {
            "domain": {
              "description": "Categories within Brand Verticals that narrow down the scope of Brands",
              "id": "46",
              "name": "Business Taxonomy"
            },
            "entity": {
              "description": "Brands, companies, advertisers and every non-person handle with the profit intent related to offline and online games such as gaming consoles, tabletop games, video game publishers",
              "id": "1557696940178935808",
              "name": "Gaming Business"
            }
          }
        ],
        "conversation_id": "1798652737896509551",
        "created_at": "2024-06-06T09:46:44.000Z",
        "edit_controls": {
          "editable_until": "2024-06-06T10:46:44.000Z",
          "edits_remaining": 5,
          "is_edit_eligible": true
        },
        "edit_history_tweet_ids": [
          "1798652737896509551"
        ],
        "entities": {
          "urls": [
            {
              "display_url": "pic.twitter.com/Odv8T9mI7E",
              "end": 67,
              "expanded_url": "https://twitter.com/Romi_nyaO_o/status/1798652737896509551/photo/1",
              "media_key": "3_1798652730241892353",
              "start": 44,
              "url": "https://t.co/Odv8T9mI7E"
            },
            {
              "display_url": "pic.twitter.com/Odv8T9mI7E",
              "end": 67,
              "expanded_url": "https://twitter.com/Romi_nyaO_o/status/1798652737896509551/photo/1",
              "media_key": "3_1798652730233540608",
              "start": 44,
              "url": "https://t.co/Odv8T9mI7E"
            }
          ]
        },
        "geo": {},
        "id": "1798652737896509551",
        "lang": "zh",
        "possibly_sensitive": false,
        "public_metrics": {
          "bookmark_count": 0,
          "impression_count": 292,
          "like_count": 4,
          "quote_count": 0,
          "reply_count": 2,
          "retweet_count": 0
        },
        "reply_settings": "everyone",
        "text": "那时候还计划要打一个5200击杀…结果后面发现真的不是每天都有精力玩游戏 也没那么开心 https://t.co/Odv8T9mI7E"
      }
    ],
    "users": [
      {
        "created_at": "2019-11-04T06:15:50.000Z",
        "description": "好想养只猫猫啊，没有猫猫的失败人",
        "entities": {
          "url": {
            "urls": [
              {
                "display_url": "google.com",
                "end": 23,
                "expanded_url": "http://www.google.com",
                "start": 0,
                "url": "https://t.co/wHF6m2Z9XX"
              }
            ]
          }
        },
        "id": "1191237542797959168",
        "location": "星河",
        "name": "Siper",
        "profile_image_url": "https://pbs.twimg.com/profile_images/1738764930801979392/RslNhxWV_normal.jpg",
        "protected": false,
        "public_metrics": {
          "followers_count": 101,
          "following_count": 326,
          "like_count": 636,
          "listed_count": 1,
          "tweet_count": 1600
        },
        "url": "https://t.co/wHF6m2Z9XX",
        "username": "Siperistic",
        "verified": false
      },
      {
        "created_at": "2023-07-03T16:30:22.000Z",
        "description": "好讨厌一个人",
        "id": "1675904773646848000",
        "name": "Romi.",
        "pinned_tweet_id": "1789148838122680725",
        "profile_image_url": "https://pbs.twimg.com/profile_images/1796854901202636800/0j3lcaR3_normal.jpg",
        "protected": false,
        "public_metrics": {
          "followers_count": 64,
          "following_count": 51,
          "like_count": 157,
          "listed_count": 0,
          "tweet_count": 398
        },
        "username": "Romi_nyaO_o",
        "verified": false
      }
    ]
  }
}