{
  "data": {
    "attachments": {},
    "author_id": "1191237542797959168",
    "conversation_id": "1787536778280542569",
    "created_at": "2024-05-07T14:54:04.000Z",
    "edit_controls": {
      "editable_until": "2024-05-07T15:54:04.000Z",
      "edits_remaining": 5,
      "is_edit_eligible": false
    },
    "edit_history_tweet_ids": [
      "1787858443602382890"
    ],
    "entities": {
      "mentions": [
        {
          "end": 16,
          "id": "1459206178529890307",
          "start": 0,
          "username": "Duchess_Coconut"
        }
      ]
    },
    "geo": {},
    "id": "1787858443602382890",
    "in_reply_to_user_id": "1459206178529890307",
    "lang": "zh",
    "possibly_sensitive": false,
    "public_metrics": {
      "bookmark_count": 0,
      "impression_count": 0,
      "like_count": 0,
      "quote_count": 0,
      "reply_count": 0,
      "retweet_count": 0
    },
    "referenced_tweets": [
      {
        "id": "1787536778280542569",
        "type": "replied_to"
      }
    ],
    "reply_settings": "everyone",
    "text": "@Duchess_Coconut 涩涩的流量确实大。。。"
  },
  "includes": {
    "tweets": [
      {
        "attachments": {},
        "author_id": "1191237542797959168",
        "conversation_id": "1787536778280542569",
        "created_at": "2024-05-07T14:54:04.000Z",
        "edit_controls": {
          "editable_until": "2024-05-07T15:54:04.000Z",
          "edits_remaining": 5,
          "is_edit_eligible": false
        },
        "edit_history_tweet_ids": [
          "1787858443602382890"
        ],
        "entities": {
          "mentions": [
            {
              "end": 16,
              "id": "1459206178529890307",
              "start": 0,
              "username": "Duchess_Coconut"
            }
          ]
        },
        "geo": {},
        "id": "1787858443602382890",
        "in_reply_to_user_id": "1459206178529890307",
        "lang": "zh",
        "possibly_sensitive": false,
        "public_metrics": {
          "bookmark_count": 0,
          "impression_count": 0,
          "like_count": 0,
          "quote_count": 0,
          "reply_count": 0,
          "retweet_count": 0
        },
        "referenced_tweets": [
          {
            "id": "1787536778280542569",
            "type": "replied_to"
          }
        ],
        "reply_settings": "everyone",
        "text": "@Duchess_Coconut 涩涩的流量确实大。。。"
      },
      {
        "attachments": {},
        "author_id": "1459206178529890307",
        "conversation_id": "1787536778280542569",
        "created_at": "2024-05-06T17:35:53.000Z",
        "edit_controls": {
          "editable_until": "2024-05-06T18:35:53.000Z",
          "edits_remaining": 5,
          "is_edit_eligible": true
        },
        "edit_history_tweet_ids": [
          "1787536778280542569"
        ],
        "entities": {},
        "geo": {},
        "id": "1787536778280542569",
        "lang": "zh",
        "possibly_sensitive": false,
        "public_metrics": {
          "bookmark_count": 0,
          "impression_count": 3632,
          "like_count": 64,
          "quote_count": 0,
          "reply_count": 8,
          "retweet_count": 0
        },
        "reply_settings": "everyone",
        "text": "现在基本只有发涩涩才能得到足够正反馈和1000以上浏览了，我本身对这个兴趣其实一般，所以其实挺失落的……也不像以前那样偶尔能认识很好的新朋友或者收到不错的私信了（甚至看黄男私信都没了＼(`Δ’)／），只能说感觉这类已经并非久留之地了😎"
      }
    ],
    "users": [
      {
        "created_at": "2019-11-04T06:15:50.000Z",
        "description": "好想养只猫猫啊，没有猫猫的失败人",
        "entities": {
          "url": {
            "urls": [
              {
                "display_url": "google.com",
                "end": 23,
                "expanded_url": "http://www.google.com",
                "start": 0,
                "url": "https://t.co/wHF6m2Z9XX"
              }
            ]
          }
        },
        "id": "1191237542797959168",
        "location": "星河",
        "name": "Siper",
        "profile_image_url": "https://pbs.twimg.com/profile_images/1738764930801979392/RslNhxWV_normal.jpg",
        "protected": false,
        "public_metrics": {
          "followers_count": 83,
          "following_count": 304,
          "like_count": 620,
          "listed_count": 1,
          "tweet_count": 1266
        },
        "url": "https://t.co/wHF6m2Z9XX",
        "username": "Siperistic",
        "verified": false
      },
      {
        "created_at": "2021-11-12T17:07:26.000Z",
        "description": "历史学与文学的愚昧拥趸者🧐|项圈、铁笼和枷锁都无法束缚的无翼猫头鹰🦉|轻小说创作者（真的吗）✒️|精神状态常年不乐观💀|IT低才生🖥️|请不要自作主张和我有过度的交流🚫|请注意账号存在工作场所不适宜内容🔞",
        "id": "1459206178529890307",
        "location": "巴达维亚",
        "name": "椰子公爵🥥",
        "pinned_tweet_id": "1760273070697451949",
        "profile_image_url": "https://pbs.twimg.com/profile_images/1778061291116244992/HkZWJ7zJ_normal.jpg",
        "protected": false,
        "public_metrics": {
          "followers_count": 6478,
          "following_count": 90,
          "like_count": 7695,
          "listed_count": 14,
          "tweet_count": 10118
        },
        "username": "Duchess_Coconut",
        "verified": false
      }
    ]
  }
}