{
  "data": {
    "attachments": {},
    "author_id": "1191237542797959168",
    "conversation_id": "1811646545567346702",
    "created_at": "2024-07-12T15:32:18.000Z",
    "edit_controls": {
      "editable_until": "2024-07-12T16:32:18.000Z",
      "edits_remaining": 5,
      "is_edit_eligible": false
    },
    "edit_history_tweet_ids": [
      "1811785663127388653"
    ],
    "entities": {
      "mentions": [
        {
          "end": 9,
          "id": "1760705336540057600",
          "start": 0,
          "username": "akiakuno"
        }
      ]
    },
    "geo": {},
    "id": "1811785663127388653",
    "in_reply_to_user_id": "1760705336540057600",
    "lang": "zh",
    "possibly_sensitive": false,
    "public_metrics": {
      "bookmark_count": 0,
      "impression_count": 0,
      "like_count": 0,
      "quote_count": 0,
      "reply_count": 0,
      "retweet_count": 0
    },
    "referenced_tweets": [
      {
        "id": "1811646545567346702",
        "type": "replied_to"
      }
    ],
    "reply_settings": "everyone",
    "text": "@akiakuno 不开心的时候把别人在心里痛骂一顿会好很多"
  },
  "includes": {
    "tweets": [
      {
        "attachments": {},
        "author_id": "1191237542797959168",
        "conversation_id": "1811646545567346702",
        "created_at": "2024-07-12T15:32:18.000Z",
        "edit_controls": {
          "editable_until": "2024-07-12T16:32:18.000Z",
          "edits_remaining": 5,
          "is_edit_eligible": false
        },
        "edit_history_tweet_ids": [
          "1811785663127388653"
        ],
        "entities": {
          "mentions": [
            {
              "end": 9,
              "id": "1760705336540057600",
              "start": 0,
              "username": "akiakuno"
            }
          ]
        },
        "geo": {},
        "id": "1811785663127388653",
        "in_reply_to_user_id": "1760705336540057600",
        "lang": "zh",
        "possibly_sensitive": false,
        "public_metrics": {
          "bookmark_count": 0,
          "impression_count": 0,
          "like_count": 0,
          "quote_count": 0,
          "reply_count": 0,
          "retweet_count": 0
        },
        "referenced_tweets": [
          {
            "id": "1811646545567346702",
            "type": "replied_to"
          }
        ],
        "reply_settings": "everyone",
        "text": "@akiakuno 不开心的时候把别人在心里痛骂一顿会好很多"
      },
      {
        "attachments": {
          "media_keys": [
            "3_1811646537640083459"
          ]
        },
        "author_id": "1760705336540057600",
        "conversation_id": "1811646545567346702",
        "created_at": "2024-07-12T06:19:29.000Z",
        "edit_controls": {
          "editable_until": "2024-07-12T07:19:29.000Z",
          "edits_remaining": 5,
          "is_edit_eligible": true
        },
        "edit_history_tweet_ids": [
          "1811646545567346702"
        ],
        "entities": {
          "urls": [
            {
              "display_url": "pic.twitter.com/5fKQ3SZnaF",
              "end": 76,
              "expanded_url": "https://twitter.com/akiakuno/status/1811646545567346702/photo/1",
              "media_key": "3_1811646537640083459",
              "start": 53,
              "url": "https://t.co/5fKQ3SZnaF"
            }
          ]
        },
        "geo": {},
        "id": "1811646545567346702",
        "lang": "zh",
        "possibly_sensitive": false,
        "public_metrics": {
          "bookmark_count": 0,
          "impression_count": 743,
          "like_count": 32,
          "quote_count": 0,
          "reply_count": 9,
          "retweet_count": 1
        },
        "reply_settings": "everyone",
        "text": "不开心的时候已经不想跟任何人倾诉，就打开推特，感觉这里虽然是粪坑，但也是很有安全感的栖息地，心里暖暖的。 https://t.co/5fKQ3SZnaF"
      }
    ],
    "users": [
      {
        "created_at": "2019-11-04T06:15:50.000Z",
        "description": "好想养只猫猫啊，没有猫猫的失败人//事一个很爱看云拍云的人//很拧巴的人//infp//似乎是个很消极的人",
        "entities": {
          "url": {
            "urls": [
              {
                "display_url": "google.com",
                "end": 23,
                "expanded_url": "http://www.google.com",
                "start": 0,
                "url": "https://t.co/wHF6m2Z9XX"
              }
            ]
          }
        },
        "id": "1191237542797959168",
        "location": "星河",
        "name": "Siper",
        "pinned_tweet_id": "1799983099612365010",
        "profile_image_url": "https://pbs.twimg.com/profile_images/1801275991010299905/UGGAiw5g_normal.jpg",
        "protected": false,
        "public_metrics": {
          "followers_count": 106,
          "following_count": 338,
          "like_count": 661,
          "listed_count": 1,
          "tweet_count": 1992
        },
        "url": "https://t.co/wHF6m2Z9XX",
        "username": "Siperistic",
        "verified": false
      },
      {
        "created_at": "2024-02-22T16:37:32.000Z",
        "description": "Life changes,why stay still.",
        "id": "1760705336540057600",
        "name": "美丽新世界",
        "pinned_tweet_id": "1802205216403591572",
        "profile_image_url": "https://pbs.twimg.com/profile_images/1771793626798145536/abxok-Vv_normal.jpg",
        "protected": false,
        "public_metrics": {
          "followers_count": 438,
          "following_count": 133,
          "like_count": 9884,
          "listed_count": 4,
          "tweet_count": 4169
        },
        "username": "akiakuno",
        "verified": false
      }
    ]
  }
}