{
  "data": {
    "article": {},
    "attachments": {},
    "author_id": "1191237542797959168",
    "conversation_id": "2040335322161291471",
    "created_at": "2026-04-04T16:19:43.000Z",
    "edit_controls": {
      "editable_until": "2026-04-04T17:19:43.000Z",
      "edits_remaining": 5,
      "is_edit_eligible": false
    },
    "edit_history_tweet_ids": [
      "2040464341141684606"
    ],
    "entities": {
      "mentions": [
        {
          "end": 16,
          "id": "1459206178529890307",
          "start": 0,
          "username": "DuchessCoconut_"
        }
      ]
    },
    "geo": {},
    "id": "2040464341141684606",
    "in_reply_to_user_id": "1459206178529890307",
    "lang": "zh",
    "note_tweet": {
      "entities": {}
    },
    "possibly_sensitive": false,
    "public_metrics": {
      "bookmark_count": 0,
      "impression_count": 0,
      "like_count": 0,
      "quote_count": 0,
      "reply_count": 0,
      "retweet_count": 0
    },
    "referenced_tweets": [
      {
        "id": "2040335322161291471",
        "type": "replied_to"
      }
    ],
    "reply_settings": "everyone",
    "text": "@DuchessCoconut_ 争议性话题会🔥但是会掉fo啊，椰子可以再多发点帖子试试嘞"
  },
  "includes": {
    "tweets": [
      {
        "article": {},
        "attachments": {},
        "author_id": "1191237542797959168",
        "conversation_id": "2040335322161291471",
        "created_at": "2026-04-04T16:19:43.000Z",
        "edit_controls": {
          "editable_until": "2026-04-04T17:19:43.000Z",
          "edits_remaining": 5,
          "is_edit_eligible": false
        },
        "edit_history_tweet_ids": [
          "2040464341141684606"
        ],
        "entities": {
          "mentions": [
            {
              "end": 16,
              "id": "1459206178529890307",
              "start": 0,
              "username": "DuchessCoconut_"
            }
          ]
        },
        "geo": {},
        "id": "2040464341141684606",
        "in_reply_to_user_id": "1459206178529890307",
        "lang": "zh",
        "note_tweet": {
          "entities": {}
        },
        "possibly_sensitive": false,
        "public_metrics": {
          "bookmark_count": 0,
          "impression_count": 0,
          "like_count": 0,
          "quote_count": 0,
          "reply_count": 0,
          "retweet_count": 0
        },
        "referenced_tweets": [
          {
            "id": "2040335322161291471",
            "type": "replied_to"
          }
        ],
        "reply_settings": "everyone",
        "text": "@DuchessCoconut_ 争议性话题会🔥但是会掉fo啊，椰子可以再多发点帖子试试嘞"
      },
      {
        "article": {},
        "attachments": {},
        "author_id": "1459206178529890307",
        "conversation_id": "2040335322161291471",
        "created_at": "2026-04-04T07:47:03.000Z",
        "edit_controls": {
          "editable_until": "2026-04-04T08:47:03.000Z",
          "edits_remaining": 5,
          "is_edit_eligible": true
        },
        "edit_history_tweet_ids": [
          "2040335322161291471"
        ],
        "entities": {},
        "geo": {},
        "id": "2040335322161291471",
        "lang": "zh",
        "note_tweet": {
          "entities": {}
        },
        "possibly_sensitive": false,
        "public_metrics": {
          "bookmark_count": 3,
          "impression_count": 7043,
          "like_count": 43,
          "quote_count": 1,
          "reply_count": 5,
          "retweet_count": 0
        },
        "reply_settings": "everyone",
        "text": "大伙能不能帮我想想发点什么炒作推文可以让椰国公涨到一万fo，我其实还是比较无所谓的毕竟推特的fo不太有用，但是果然还是人类对十进制的成瘾占了上风，唉已经卡在九千六七百大半年了……꒦ິ^꒦ິ"
      }
    ],
    "users": [
      {
        "created_at": "2019-11-04T06:15:50.000Z",
        "description": "好想养只猫猫啊//是一个很爱看云拍云的人//很拧巴的人//infp//似乎是个很消极的人//喜欢看大家的碎碎念日常//喜欢到处跑去评论//欲窥天地                           匿名信箱欢迎提问~https://t.co/d5X5RjhXaU",
        "entities": {
          "description": {
            "urls": [
              {
                "display_url": "ngl.link/siperistic53283",
                "end": 132,
                "expanded_url": "http://ngl.link/siperistic53283",
                "start": 109,
                "url": "https://t.co/d5X5RjhXaU"
              }
            ]
          },
          "url": {
            "urls": [
              {
                "display_url": "google.com",
                "end": 23,
                "expanded_url": "http://www.google.com",
                "start": 0,
                "url": "https://t.co/wHF6m2Z9XX"
              }
            ]
          }
        },
        "id": "1191237542797959168",
        "location": "星河",
        "name": "Siper",
        "pinned_tweet_id": "1851481166446199274",
        "profile_image_url": "https://pbs.twimg.com/profile_images/1801275991010299905/UGGAiw5g_normal.jpg",
        "protected": false,
        "public_metrics": {
          "followers_count": 208,
          "following_count": 619,
          "like_count": 699,
          "listed_count": 3,
          "media_count": 338,
          "tweet_count": 5430
        },
        "url": "https://t.co/wHF6m2Z9XX",
        "username": "Siperistic",
        "verified": false
      },
      {
        "created_at": "2021-11-12T17:07:26.000Z",
        "description": "=椰子|历史学与文学的愚昧拥趸者🧐|铁笼和枷锁都无法束缚的无翼猫头鹰🦉|轻小说创作者（真的吗）✒️|弄oc的请看看咱小怪盗和其他孩子谢谢👻|oc图都是约稿我不会画画TT🎨|精神状态常年不乐观💀|感觉人类很可怕所以私信不太回🚫|会直接无差别屏蔽让人反感或不安的账号👁️|请注意账号存在工作场所不适宜内容🔞",
        "id": "1459206178529890307",
        "location": "星馐阁",
        "name": "椰子公爵🥥",
        "pinned_tweet_id": "1942593215066169560",
        "profile_image_url": "https://pbs.twimg.com/profile_images/2039753721689853952/_mPWZooR_normal.jpg",
        "protected": false,
        "public_metrics": {
          "followers_count": 9851,
          "following_count": 165,
          "like_count": 16918,
          "listed_count": 22,
          "media_count": 3980,
          "tweet_count": 16154
        },
        "username": "DuchessCoconut_",
        "verified": false
      }
    ]
  }
}